{
    "Hills": [
        {
            "Id": 40001,
            "Vertices": [
                {
                    "X": -25.8437,
                    "Y": 3.59211
                },
                {
                    "X": -10.220724087645344,
                    "Y": 46.575086389491545
                },
                {
                    "X": 8.858454099199534,
                    "Y": 47.67159088298838
                },
                {
                    "X": 18.5077,
                    "Y": 24.4257
                }
            ]
        },
        {
            "Id": 40000,
            "Vertices": [
                {
                    "X": 23.167871749486935,
                    "Y": 36.31120476458979
                },
                {
                    "X": 22.000234305563637,
                    "Y": 0.2643686507672598
                },
                {
                    "X": 55.51142894616228,
                    "Y": -4.042111769910655
                },
                {
                    "X": 35.1945374218969,
                    "Y": 30.888229420032417
                }
            ]
        }
    ],
    "Targets": [
        {
            "Id": 10000,
            "X": 7.919552991488025,
            "Y": 16.55916271383264
        },
        {
            "Id": 10001,
            "X": -13.889921384163955,
            "Y": 47.129707992524295
        },
        {
            "Id": 10002,
            "X": 19.663116116839085,
            "Y": 24.947422089083396
        },
        {
            "Id": 10003,
            "X": -23.396615342781484,
            "Y": -3.3862540228747164
        },
        {
            "Id": 10004,
            "X": 59.92676111804275,
            "Y": -2.08141367561349
        },
        {
            "Id": 10005,
            "X": 12.20688556106063,
            "Y": -10.096861523075326
        },
        {
            "Id": 10006,
            "X": 18.122479668419928,
            "Y": 62.43950441037006
        },
        {
            "Id": 10007,
            "X": 46.11954787154053,
            "Y": -26.576930968956088
        }
    ],
    "Trappy_Circles": [
        {
            "Id": 20000,
            "Radius": 10.14584,
            "X": 0.883362,
            "Y": 3.76028
        },
        {
            "Id": 20004,
            "Radius": 7.098120017227275,
            "X": 14.343409181715266,
            "Y": 52.865085174213014
        },
        {
            "Id": 20002,
            "Radius": 1.2906186630113354,
            "X": 58.37746878313216,
            "Y": -3.005475947971121
        },
        {
            "Id": 20001,
            "Radius": 6.871468522371515,
            "X": 15.009247865260352,
            "Y": 14.817571670134896
        },
        {
            "Id": 20003,
            "Radius": 9.108004552405431,
            "X": 45.597530738654505,
            "Y": -16.452272507642146
        }
    ],
    "Trappy_Lines": [
        {
            "Id": 30001,
            "Id_P1": 10006,
            "Id_P2": 10004
        }
    ]
}
